{
  "type": "FeatureCollection",
  "features": [
    {
      "type": "Feature",
      "geometry": {
        "type": "Polygon",
        "coordinates": [
          [
            [
              -97.0601793593805,
              33.3543897382127
            ],
            [
              -96.9481406904437,
              33.34615145207117
            ],
            [
              -96.83956780873369,
              33.321691502118505
            ],
            [
              -96.73781354325696,
              33.281766292822425
            ],
            [
              -96.64600922450032,
              33.22760909007483
            ],
            [
              -96.56696470923937,
              33.16089003704802
            ],
            [
              -96.50308060595745,
              33.083662360432434
            ],
            [
              -96.45627563825504,
              32.99829679076744
            ],
            [
              -96.42793126935727,
              32.90740658995094
            ],
            [
              -96.41885485561446,
              32.8137658232796
            ],
            [
              -96.42926177035773,
              32.72022363301921
            ],
            [
              -96.45877619738671,
              32.62961727539609
            ],
            [
              -96.50644967279837,
              32.544686589475255
            ],
            [
              -96.57079597202251,
              32.46799239450003
            ],
            [
              -96.64984059512271,
              32.401841082264106
            ],
            [
              -96.74118288315644,
              32.34821740154115
            ],
            [
              -96.8420686783761,
              32.30872713786152
            ],
            [
              -96.94947139411563,
              32.28455108551184
            ],
            [
              -97.0601793593805,
              32.27641139726928
            ],
            [
              -97.17088732464538,
              32.28455108551184
            ],
            [
              -97.27829004038492,
              32.30872713786152
            ],
            [
              -97.37917583560457,
              32.34821740154115
            ],
            [
              -97.4705181236383,
              32.401841082264106
            ],
            [
              -97.5495627467385,
              32.46799239450003
            ],
            [
              -97.61390904596264,
              32.544686589475255
            ],
            [
              -97.6615825213743,
              32.62961727539609
            ],
            [
              -97.69109694840328,
              32.72022363301921
            ],
            [
              -97.70150386314656,
              32.8137658232796
            ],
            [
              -97.69242744940374,
              32.90740658995094
            ],
            [
              -97.66408308050597,
              32.99829679076744
            ],
            [
              -97.61727811280356,
              33.083662360432434
            ],
            [
              -97.55339400952164,
              33.16089003704802
            ],
            [
              -97.4743494942607,
              33.22760909007483
            ],
            [
              -97.38254517550405,
              33.281766292822425
            ],
            [
              -97.28079091002732,
              33.321691502118505
            ],
            [
              -97.17221802831732,
              33.34615145207117
            ],
            [
              -97.0601793593805,
              33.3543897382127
            ]
          ]
        ]
      },
      "properties": {
        "name": "Search Area",
        "radius": 60000
      }
    },
    {
      "type": "Feature",
      "geometry": {
        "type": "Point",
        "coordinates": [
          -97.1352208,
          32.6710216
        ]
      },
      "properties": {
        "id": 1,
        "name": "Royal Tea",
        "address": "4654 S Cooper St #340, Arlington"
      }
    },
    {
      "type": "Feature",
      "geometry": {
        "type": "Point",
        "coordinates": [
          -97.1328633,
          32.679396
        ]
      },
      "properties": {
        "id": 2,
        "name": "Tea Scoop Boba Tea & Smoothie",
        "address": "4133 S Cooper St SUITE 303, Arlington"
      }
    },
    {
      "type": "Feature",
      "geometry": {
        "type": "Point",
        "coordinates": [
          -97.3980143,
          32.6781058
        ]
      },
      "properties": {
        "id": 3,
        "name": "Kokee Tea",
        "address": "4800 S Hulen St #250, Fort Worth"
      }
    },
    {
      "type": "Feature",
      "geometry": {
        "type": "Point",
        "coordinates": [
          -96.6548895,
          32.9725761
        ]
      },
      "properties": {
        "id": 4,
        "name": "King Kong Boba Tea & Smoothie",
        "address": "6313 N President George Bush Hwy Ste 100, Garland"
      }
    },
    {
      "type": "Feature",
      "geometry": {
        "type": "Point",
        "coordinates": [
          -96.7648305,
          33.0000936
        ]
      },
      "properties": {
        "id": 5,
        "name": "Rainbow Teashop Boba (Toco Toco)",
        "address": "3801 W President George Bush Hwy #116, Plano"
      }
    },
    {
      "type": "Feature",
      "geometry": {
        "type": "Point",
        "coordinates": [
          -96.76852509999999,
          32.8597195
        ]
      },
      "properties": {
        "id": 6,
        "name": "Craft Boba Tea",
        "address": "6105 Greenville Ave, Dallas"
      }
    },
    {
      "type": "Feature",
      "geometry": {
        "type": "Point",
        "coordinates": [
          -96.8047242,
          33.1085339
        ]
      },
      "properties": {
        "id": 7,
        "name": "Vivi Bubble Tea",
        "address": "3520 Preston Rd #108, Frisco"
      }
    },
    {
      "type": "Feature",
      "geometry": {
        "type": "Point",
        "coordinates": [
          -97.4017964,
          32.6771232
        ]
      },
      "properties": {
        "id": 8,
        "name": "Kung Fu Tea",
        "address": "4946 Overton Ridge Blvd, Fort Worth"
      }
    },
    {
      "type": "Feature",
      "geometry": {
        "type": "Point",
        "coordinates": [
          -96.8281793,
          32.7482307
        ]
      },
      "properties": {
        "id": 9,
        "name": "Craft Boba Tea",
        "address": "408 N Bishop Ave # 104, Dallas"
      }
    },
    {
      "type": "Feature",
      "geometry": {
        "type": "Point",
        "coordinates": [
          -96.61327639999999,
          32.9517457
        ]
      },
      "properties": {
        "id": 10,
        "name": "Vivi Bubble Tea",
        "address": "325 Coneflower Dr, Garland"
      }
    },
    {
      "type": "Feature",
      "geometry": {
        "type": "Point",
        "coordinates": [
          -97.3563487,
          32.7482785
        ]
      },
      "properties": {
        "id": 11,
        "name": "Happy Lemon",
        "address": "1019 Foch St, Fort Worth"
      }
    },
    {
      "type": "Feature",
      "geometry": {
        "type": "Point",
        "coordinates": [
          -96.69461299999999,
          33.06730599999999
        ]
      },
      "properties": {
        "id": 12,
        "name": "bobaLand",
        "address": "240 Legacy Dr #110, Plano"
      }
    },
    {
      "type": "Feature",
      "geometry": {
        "type": "Point",
        "coordinates": [
          -97.1063054,
          32.7357183
        ]
      },
      "properties": {
        "id": 13,
        "name": "Kung Fu Tea",
        "address": "101 E Abram St Suite 170, Arlington"
      }
    },
    {
      "type": "Feature",
      "geometry": {
        "type": "Point",
        "coordinates": [
          -96.78705570000001,
          32.8213944
        ]
      },
      "properties": {
        "id": 14,
        "name": "Kung Fu Tea",
        "address": "3001 Knox St #107A, Dallas"
      }
    },
    {
      "type": "Feature",
      "geometry": {
        "type": "Point",
        "coordinates": [
          -97.11535649999999,
          32.7238035
        ]
      },
      "properties": {
        "id": 15,
        "name": "DING TEA S Cooper St",
        "address": "1302 S Cooper St, Arlington"
      }
    },
    {
      "type": "Feature",
      "geometry": {
        "type": "Point",
        "coordinates": [
          -96.8889968,
          32.97434
        ]
      },
      "properties": {
        "id": 16,
        "name": "Fruitealicious Boba Tea",
        "address": "2150 N Josey Ln Apt 100, Carrollton"
      }
    },
    {
      "type": "Feature",
      "geometry": {
        "type": "Point",
        "coordinates": [
          -96.602066,
          32.8148574
        ]
      },
      "properties": {
        "id": 17,
        "name": "Bubble Leaf Boba Lounge",
        "address": "427 N Town E Blvd Suite 109, Mesquite"
      }
    },
    {
      "type": "Feature",
      "geometry": {
        "type": "Point",
        "coordinates": [
          -96.6805461,
          32.9457604
        ]
      },
      "properties": {
        "id": 18,
        "name": "Boba Heaven",
        "address": "3112 N Jupiter Rd suite 311, Garland"
      }
    },
    {
      "type": "Feature",
      "geometry": {
        "type": "Point",
        "coordinates": [
          -96.7697724,
          32.8537415
        ]
      },
      "properties": {
        "id": 19,
        "name": "Panda Tea",
        "address": "5521 Greenville Ave #108, Dallas"
      }
    },
    {
      "type": "Feature",
      "geometry": {
        "type": "Point",
        "coordinates": [
          -97.0462077,
          32.7101563
        ]
      },
      "properties": {
        "id": 20,
        "name": "Gong Cha Grand Prairie",
        "address": "2625 W Pioneer Pkwy #202, Grand Prairie"
      }
    },
    {
      "type": "Feature",
      "geometry": {
        "type": "Point",
        "coordinates": [
          -96.82904459999999,
          32.7783711
        ]
      },
      "properties": {
        "id": 21,
        "name": "Craft Boba Tea",
        "address": "320 Singleton Blvd #180, Dallas"
      }
    },
    {
      "type": "Feature",
      "geometry": {
        "type": "Point",
        "coordinates": [
          -96.73228739999999,
          33.1298128
        ]
      },
      "properties": {
        "id": 22,
        "name": "Delish Bubble Tea",
        "address": "8930 State Hwy 121, McKinney"
      }
    },
    {
      "type": "Feature",
      "geometry": {
        "type": "Point",
        "coordinates": [
          -97.10903309999999,
          32.70698600000001
        ]
      },
      "properties": {
        "id": 23,
        "name": "rocketbelly",
        "address": "100 W Pioneer Pkwy Ste. 156, Arlington"
      }
    },
    {
      "type": "Feature",
      "geometry": {
        "type": "Point",
        "coordinates": [
          -97.32355849999999,
          32.9029121
        ]
      },
      "properties": {
        "id": 24,
        "name": "Sharetea Fort Worth",
        "address": "8949 Tehama Ridge Pkwy, Fort Worth"
      }
    },
    {
      "type": "Feature",
      "geometry": {
        "type": "Point",
        "coordinates": [
          -96.81694189999999,
          32.9334484
        ]
      },
      "properties": {
        "id": 25,
        "name": "Fat Straws Boba & Mochi Donuts (Alpha & Noel)",
        "address": "5301 Alpha Rd #38, Dallas"
      }
    },
    {
      "type": "Feature",
      "geometry": {
        "type": "Point",
        "coordinates": [
          -96.6924531,
          33.0665652
        ]
      },
      "properties": {
        "id": 26,
        "name": "Boba Republic Plano",
        "address": "100 Legacy Dr #102, Plano"
      }
    },
    {
      "type": "Feature",
      "geometry": {
        "type": "Point",
        "coordinates": [
          -96.8413502,
          32.9548007
        ]
      },
      "properties": {
        "id": 27,
        "name": "Boba Tea & Treats",
        "address": "4135 Belt Line Rd, Addison"
      }
    },
    {
      "type": "Feature",
      "geometry": {
        "type": "Point",
        "coordinates": [
          -97.0606077,
          32.646518
        ]
      },
      "properties": {
        "id": 28,
        "name": "Kung Fu Tea",
        "address": "5220 S State Hwy 360 #120, Grand Prairie"
      }
    },
    {
      "type": "Feature",
      "geometry": {
        "type": "Point",
        "coordinates": [
          -97.41538039999999,
          32.7295364
        ]
      },
      "properties": {
        "id": 29,
        "name": "1102 Express Bubble Tea & Coffee",
        "address": "3204 Winthrop Ave, Fort Worth"
      }
    },
    {
      "type": "Feature",
      "geometry": {
        "type": "Point",
        "coordinates": [
          -96.9078453,
          32.9815723
        ]
      },
      "properties": {
        "id": 30,
        "name": "Kung Fu Tea",
        "address": "2540 Old Denton Rd Suite 122, Carrollton"
      }
    },
    {
      "type": "Feature",
      "geometry": {
        "type": "Point",
        "coordinates": [
          -96.91043850000001,
          32.9844759
        ]
      },
      "properties": {
        "id": 31,
        "name": "Sharetea",
        "address": "2601 Old Denton Rd, Carrollton"
      }
    },
    {
      "type": "Feature",
      "geometry": {
        "type": "Point",
        "coordinates": [
          -96.8878611,
          33.0627301
        ]
      },
      "properties": {
        "id": 32,
        "name": "Teapioca Lounge",
        "address": "6225 N Josey Ln #114, Lewisville"
      }
    },
    {
      "type": "Feature",
      "geometry": {
        "type": "Point",
        "coordinates": [
          -96.7006578,
          32.947141
        ]
      },
      "properties": {
        "id": 33,
        "name": "Happy Lemon",
        "address": "169 N Plano Rd, Richardson"
      }
    },
    {
      "type": "Feature",
      "geometry": {
        "type": "Point",
        "coordinates": [
          -97.1685524,
          33.2292705
        ]
      },
      "properties": {
        "id": 34,
        "name": "Kung Fu Tea",
        "address": "2735 W University Dr #1061, Denton"
      }
    },
    {
      "type": "Feature",
      "geometry": {
        "type": "Point",
        "coordinates": [
          -96.8048561,
          33.0893713
        ]
      },
      "properties": {
        "id": 35,
        "name": "The Alley Tea - Caf\u00e9 - Life",
        "address": "8240 Preston Rd Suite 177, Plano"
      }
    },
    {
      "type": "Feature",
      "geometry": {
        "type": "Point",
        "coordinates": [
          -97.28950800000001,
          32.862718
        ]
      },
      "properties": {
        "id": 36,
        "name": "Gong Cha Fort Worth",
        "address": "6650 N Beach St Ste 100, Fort Worth"
      }
    },
    {
      "type": "Feature",
      "geometry": {
        "type": "Point",
        "coordinates": [
          -96.84172029999999,
          33.0270648
        ]
      },
      "properties": {
        "id": 37,
        "name": "Fat Straws Boba & Mochi Donuts (Plano)",
        "address": "6509 W Park Blvd #425, Plano"
      }
    },
    {
      "type": "Feature",
      "geometry": {
        "type": "Point",
        "coordinates": [
          -97.1319003,
          32.6871474
        ]
      },
      "properties": {
        "id": 38,
        "name": "1102 Bubble Tea & Bites",
        "address": "3610 S Cooper St #110B, Arlington"
      }
    },
    {
      "type": "Feature",
      "geometry": {
        "type": "Point",
        "coordinates": [
          -96.7160404,
          32.9770868
        ]
      },
      "properties": {
        "id": 39,
        "name": "Kung Fu Tea",
        "address": "2067 N Central Expy #100, Richardson"
      }
    },
    {
      "type": "Feature",
      "geometry": {
        "type": "Point",
        "coordinates": [
          -96.6578694,
          33.2178735
        ]
      },
      "properties": {
        "id": 40,
        "name": "Exotic Blendz Bubble Tea",
        "address": "3540 W University Dr STE 300, McKinney"
      }
    },
    {
      "type": "Feature",
      "geometry": {
        "type": "Point",
        "coordinates": [
          -96.7074798,
          33.0400518
        ]
      },
      "properties": {
        "id": 41,
        "name": "Happy Lemon",
        "address": "301 W Parker Rd #103, Plano"
      }
    },
    {
      "type": "Feature",
      "geometry": {
        "type": "Point",
        "coordinates": [
          -96.5671668,
          32.9065695
        ]
      },
      "properties": {
        "id": 42,
        "name": "Feng Cha Rowlett",
        "address": "3526 Lakeview Pkwy, Rowlett"
      }
    },
    {
      "type": "Feature",
      "geometry": {
        "type": "Point",
        "coordinates": [
          -96.6999629,
          33.0185372
        ]
      },
      "properties": {
        "id": 43,
        "name": "The Whale Tea",
        "address": "1009 14th St Unit 600, Plano"
      }
    },
    {
      "type": "Feature",
      "geometry": {
        "type": "Point",
        "coordinates": [
          -96.9913521,
          32.8393761
        ]
      },
      "properties": {
        "id": 44,
        "name": "Zero Degrees",
        "address": "3401 W Airport Fwy # 138, Irving"
      }
    },
    {
      "type": "Feature",
      "geometry": {
        "type": "Point",
        "coordinates": [
          -97.158514,
          33.2301203
        ]
      },
      "properties": {
        "id": 45,
        "name": "Sharetea Denton",
        "address": "2200 W University Dr Suite 160, Denton"
      }
    },
    {
      "type": "Feature",
      "geometry": {
        "type": "Point",
        "coordinates": [
          -97.0417512,
          32.9679736
        ]
      },
      "properties": {
        "id": 46,
        "name": "Bubble Tea Bliss",
        "address": "3000 Grapevine Mills Pkwy, Grapevine"
      }
    },
    {
      "type": "Feature",
      "geometry": {
        "type": "Point",
        "coordinates": [
          -96.95970270000001,
          32.8537908
        ]
      },
      "properties": {
        "id": 47,
        "name": "BUBBLE SHUBBLE BOBA TEA \u062d\u0644\u0627\u0644 / BEST BOBA TEA IN IRVING",
        "address": "1111 Coker St, Irving"
      }
    },
    {
      "type": "Feature",
      "geometry": {
        "type": "Point",
        "coordinates": [
          -96.8429432,
          32.4115083
        ]
      },
      "properties": {
        "id": 48,
        "name": "ABC Boba Tea & Smoothie",
        "address": "791 N Hwy 77 Suite 501-A1, Waxahachie"
      }
    },
    {
      "type": "Feature",
      "geometry": {
        "type": "Point",
        "coordinates": [
          -96.6793823,
          33.1433792
        ]
      },
      "properties": {
        "id": 49,
        "name": "Boba Republic",
        "address": "975 State Hwy 121 #160, Allen"
      }
    },
    {
      "type": "Feature",
      "geometry": {
        "type": "Point",
        "coordinates": [
          -96.91042329999999,
          32.9866546
        ]
      },
      "properties": {
        "id": 50,
        "name": "Tiger Sugar",
        "address": "2625 Old Denton Rd #555, Carrollton"
      }
    },
    {
      "type": "Feature",
      "geometry": {
        "type": "Point",
        "coordinates": [
          -96.6100091,
          33.010608
        ]
      },
      "properties": {
        "id": 51,
        "name": "Kung Fu Tea",
        "address": "160 FM 544 Suite 90, Murphy"
      }
    },
    {
      "type": "Feature",
      "geometry": {
        "type": "Point",
        "coordinates": [
          -96.6948409,
          33.0578339
        ]
      },
      "properties": {
        "id": 52,
        "name": "Tiger Sugar",
        "address": "101 W Spring Creek Pkwy # 735, Plano"
      }
    },
    {
      "type": "Feature",
      "geometry": {
        "type": "Point",
        "coordinates": [
          -96.9084722,
          32.9847829
        ]
      },
      "properties": {
        "id": 53,
        "name": "R&B TEA CARROLLTON",
        "address": "1017 E Trinity Mls Rd Apt 100, Carrollton"
      }
    },
    {
      "type": "Feature",
      "geometry": {
        "type": "Point",
        "coordinates": [
          -96.6823551,
          33.1506594
        ]
      },
      "properties": {
        "id": 54,
        "name": "Boba City",
        "address": "5160 Collin McKinney Pkwy #100, McKinney"
      }
    },
    {
      "type": "Feature",
      "geometry": {
        "type": "Point",
        "coordinates": [
          -96.7343808,
          32.948823
        ]
      },
      "properties": {
        "id": 55,
        "name": "His Tea",
        "address": "221 W Polk St #105, Richardson"
      }
    },
    {
      "type": "Feature",
      "geometry": {
        "type": "Point",
        "coordinates": [
          -96.9864336,
          33.0045746
        ]
      },
      "properties": {
        "id": 56,
        "name": "Boba World",
        "address": "291 E Round Grove Rd #190, Lewisville"
      }
    },
    {
      "type": "Feature",
      "geometry": {
        "type": "Point",
        "coordinates": [
          -96.7094977,
          33.0294854
        ]
      },
      "properties": {
        "id": 57,
        "name": "Gong Cha Plano",
        "address": "2205 N Central Expy, Plano"
      }
    },
    {
      "type": "Feature",
      "geometry": {
        "type": "Point",
        "coordinates": [
          -96.76982,
          32.907896
        ]
      },
      "properties": {
        "id": 58,
        "name": "Gong Cha Dallas",
        "address": "11613 N Central Expy #106a, Dallas"
      }
    },
    {
      "type": "Feature",
      "geometry": {
        "type": "Point",
        "coordinates": [
          -96.6005949,
          33.0119702
        ]
      },
      "properties": {
        "id": 59,
        "name": "Boba-Lush",
        "address": "511 FM 544 Suite 107, Murphy"
      }
    },
    {
      "type": "Feature",
      "geometry": {
        "type": "Point",
        "coordinates": [
          -96.81213629999999,
          33.1034194
        ]
      },
      "properties": {
        "id": 60,
        "name": "Fruitealicious Bubble Tea & Smoothies",
        "address": "8300 Gaylord Pkwy Suite#14, Frisco"
      }
    },
    {
      "type": "Feature",
      "geometry": {
        "type": "Point",
        "coordinates": [
          -97.11378560000001,
          32.7197827
        ]
      },
      "properties": {
        "id": 61,
        "name": "Unitea Bubble Tea",
        "address": "614 W Park Row Dr, Arlington"
      }
    },
    {
      "type": "Feature",
      "geometry": {
        "type": "Point",
        "coordinates": [
          -97.3580556,
          32.7066667
        ]
      },
      "properties": {
        "id": 62,
        "name": "Fruitealicious Bubble Tea & Smoothies",
        "address": "3043 Greene Ave, Fort Worth"
      }
    },
    {
      "type": "Feature",
      "geometry": {
        "type": "Point",
        "coordinates": [
          -96.7717072,
          33.0279817
        ]
      },
      "properties": {
        "id": 63,
        "name": "Kung Fu Tea",
        "address": "2001 Coit Rd Suite 137, Plano"
      }
    },
    {
      "type": "Feature",
      "geometry": {
        "type": "Point",
        "coordinates": [
          -96.9080115,
          32.9800541
        ]
      },
      "properties": {
        "id": 64,
        "name": "FENG CHA",
        "address": "2528 Old Denton Rd #150, Carrollton"
      }
    },
    {
      "type": "Feature",
      "geometry": {
        "type": "Point",
        "coordinates": [
          -97.13010489999999,
          32.6798877
        ]
      },
      "properties": {
        "id": 65,
        "name": "Kokee Tea",
        "address": "3811 S Cooper St #2052, Arlington"
      }
    },
    {
      "type": "Feature",
      "geometry": {
        "type": "Point",
        "coordinates": [
          -96.90684510000001,
          32.9505877
        ]
      },
      "properties": {
        "id": 66,
        "name": "MILK T BAR",
        "address": "1414 S Broadway St #3-3113, Carrollton"
      }
    },
    {
      "type": "Feature",
      "geometry": {
        "type": "Point",
        "coordinates": [
          -96.8183945,
          32.9277378
        ]
      },
      "properties": {
        "id": 67,
        "name": "Sharetea",
        "address": "13350 Dallas Pkwy #410, Dallas"
      }
    },
    {
      "type": "Feature",
      "geometry": {
        "type": "Point",
        "coordinates": [
          -96.81768579999999,
          32.9549655
        ]
      },
      "properties": {
        "id": 68,
        "name": "Feng Cha - Belt Line Dallas",
        "address": "5225 Belt Line Rd #254, Dallas"
      }
    },
    {
      "type": "Feature",
      "geometry": {
        "type": "Point",
        "coordinates": [
          -96.9103902,
          32.9882362
        ]
      },
      "properties": {
        "id": 69,
        "name": "Gong Cha",
        "address": "2701 Old Denton Rd Ste 120, Carrollton"
      }
    },
    {
      "type": "Feature",
      "geometry": {
        "type": "Point",
        "coordinates": [
          -97.08107369999999,
          32.7077872
        ]
      },
      "properties": {
        "id": 70,
        "name": "Happy Lemon",
        "address": "1818 E Pioneer Pkwy suite 166, Arlington"
      }
    },
    {
      "type": "Feature",
      "geometry": {
        "type": "Point",
        "coordinates": [
          -97.0885181,
          32.5748152
        ]
      },
      "properties": {
        "id": 71,
        "name": "Sharetea Mansfield",
        "address": "3141 E Broad St suite 109, Mansfield"
      }
    },
    {
      "type": "Feature",
      "geometry": {
        "type": "Point",
        "coordinates": [
          -96.81008829999999,
          33.0998463
        ]
      },
      "properties": {
        "id": 72,
        "name": "Kung Fu Tea",
        "address": "Between (JCPenney and Dick\u2019s Sporting Good\u2019s) at Stonebriar Centre, 2601 Preston Rd Kiosk #5614, Frisco"
      }
    },
    {
      "type": "Feature",
      "geometry": {
        "type": "Point",
        "coordinates": [
          -96.6786395,
          32.9456523
        ]
      },
      "properties": {
        "id": 73,
        "name": "DING TEA GARLAND",
        "address": "3317 Belt Line Rd, Garland"
      }
    },
    {
      "type": "Feature",
      "geometry": {
        "type": "Point",
        "coordinates": [
          -96.7394984,
          32.976925
        ]
      },
      "properties": {
        "id": 74,
        "name": "Ding Tea Richardson",
        "address": "581 W Campbell Rd, Richardson"
      }
    },
    {
      "type": "Feature",
      "geometry": {
        "type": "Point",
        "coordinates": [
          -97.29030639999999,
          32.8749967
        ]
      },
      "properties": {
        "id": 75,
        "name": "Feng Cha-North Fort Worth",
        "address": "7451 N Beach St Ste 180, Fort Worth"
      }
    },
    {
      "type": "Feature",
      "properties": {
        "marker-color": "#1c5932",
        "marker-size": "medium",
        "marker-symbol": "cafe",
        "name": "Timekeeper's Haus",
        "id": 76
      },
      "geometry": {
        "coordinates": [
          -97.23504427657171,
          33.13097255140205
        ],
        "type": "Point"
      }
    },
    {
      "type": "Feature",
      "properties": {
        "stroke": "#555555",
        "stroke-width": 2,
        "stroke-opacity": 1,
        "fill": "#fb0404",
        "fill-opacity": 0.5,
        "id": 78
      },
      "geometry": {
        "type": "Polygon",
        "coordinates": [
          [
            [
              -97.23371531116045,
              33.241179481034166
            ],
            [
              -97.24681463221584,
              33.240640564032944
            ],
            [
              -97.25978731971753,
              33.23902902291537
            ],
            [
              -97.27250797822776,
              33.23636043639754
            ],
            [
              -97.2848536758929,
              33.23266059971977
            ],
            [
              -97.29670514476663,
              33.227965272533055
            ],
            [
              -97.30794794378936,
              33.22231982955001
            ],
            [
              -97.31847357266619,
              33.21577881751882
            ],
            [
              -97.3281805254625,
              33.20840542302263
            ],
            [
              -97.33697527343702,
              33.20027085649813
            ],
            [
              -97.34477316744874,
              33.191453658695735
            ],
            [
              -97.35149925118841,
              33.1820389365612
            ],
            [
              -97.35708897748837,
              33.17211753619674
            ],
            [
              -97.36148882103544,
              33.161785161152494
            ],
            [
              -97.36465678193954,
              33.15114144480168
            ],
            [
              -97.36656277577615,
              33.140288985960495
            ],
            [
              -97.36718890691039,
              33.129332357224925
            ],
            [
              -97.36652962310762,
              33.11837709570959
            ],
            [
              -97.3645917506279,
              33.10752868598838
            ],
            [
              -97.36139441017345,
              33.09689154505402
            ],
            [
              -97.356968815201,
              33.08656801903634
            ],
            [
              -97.3513579552109,
              33.07665740124919
            ],
            [
              -97.3446161676748,
              33.06725498087812
            ],
            [
              -97.3368086032558,
              33.05845113127866
            ],
            [
              -97.32801058990256,
              33.05033044643476
            ],
            [
              -97.31830690225581,
              33.04297093363239
            ],
            [
              -97.30779094359197,
              33.03644326984178
            ],
            [
              -97.29656384823588,
              33.03081012867853
            ],
            [
              -97.2847335130067,
              33.026125584135585
            ],
            [
              -97.27241356681252,
              33.02243459655083
            ],
            [
              -97.25972228798247,
              33.01977258550578
            ],
            [
              -97.24678147931814,
              33.018165093545825
            ],
            [
              -97.23371531116045,
              33.017627543778076
            ],
            [
              -97.22064914300275,
              33.018165093545825
            ],
            [
              -97.20770833433843,
              33.01977258550578
            ],
            [
              -97.19501705550839,
              33.02243459655083
            ],
            [
              -97.1826971093142,
              33.026125584135585
            ],
            [
              -97.17086677408501,
              33.03081012867853
            ],
            [
              -97.15963967872894,
              33.03644326984178
            ],
            [
              -97.14912372006508,
              33.04297093363239
            ],
            [
              -97.13942003241833,
              33.05033044643476
            ],
            [
              -97.13062201906509,
              33.05845113127866
            ],
            [
              -97.1228144546461,
              33.06725498087812
            ],
            [
              -97.11607266710999,
              33.07665740124919
            ],
            [
              -97.11046180711989,
              33.08656801903634
            ],
            [
              -97.10603621214744,
              33.09689154505402
            ],
            [
              -97.102838871693,
              33.10752868598838
            ],
            [
              -97.10090099921327,
              33.11837709570959
            ],
            [
              -97.10024171541052,
              33.129332357224925
            ],
            [
              -97.10086784654474,
              33.140288985960495
            ],
            [
              -97.10277384038136,
              33.15114144480168
            ],
            [
              -97.10594180128545,
              33.161785161152494
            ],
            [
              -97.11034164483252,
              33.17211753619674
            ],
            [
              -97.11593137113249,
              33.1820389365612
            ],
            [
              -97.12265745487215,
              33.191453658695735
            ],
            [
              -97.13045534888388,
              33.20027085649813
            ],
            [
              -97.13925009685842,
              33.20840542302263
            ],
            [
              -97.1489570496547,
              33.21577881751882
            ],
            [
              -97.15948267853155,
              33.22231982955001
            ],
            [
              -97.17072547755426,
              33.227965272533055
            ],
            [
              -97.18257694642799,
              33.23266059971977
            ],
            [
              -97.19492264409314,
              33.23636043639754
            ],
            [
              -97.20764330260336,
              33.23902902291537
            ],
            [
              -97.22061599010506,
              33.240640564032944
            ],
            [
              -97.23371531116045,
              33.241179481034166
            ]
          ]
        ]
      }
    }
  ]
}